[
  {
    "sample_idx": 0,
    "pred_prob": 0.20688162744045258,
    "pred_label": 0,
    "intercept": 0.34113749475213717,
    "features": [
      [
        "global_alpha_peak_pw_p95",
        -0.061755635675178375
      ],
      [
        "global_aperiodic_exponent_p95",
        0.040151125514211475
      ],
      [
        "net8_Default_Mode_aperiodic_exponent_p95",
        0.03809074707848496
      ],
      [
        "net8_Default_Mode_alpha_peak_bw_p95",
        0.037107201412122245
      ],
      [
        "net8_Visual_aperiodic_exponent_p95",
        0.025206149012374352
      ],
      [
        "net8_Dorsal_Attention_alpha_peak_pw_p5",
        -0.025122695844078276
      ],
      [
        "global_aperiodic_exponent_p5",
        -0.01983416244210368
      ],
      [
        "net8_Limbic_alpha_peak_bw_p95",
        0.018458742365938065
      ],
      [
        "net8_Default_Mode_aperiodic_exponent_median",
        -0.012780937532560056
      ],
      [
        "net8_Visual_aperiodic_offset_p95",
        -0.012059397590660043
      ],
      [
        "net8_Dorsal_Attention_aperiodic_offset_p95",
        -0.011891109076675727
      ],
      [
        "global_aperiodic_offset_p95",
        -0.010059724241093951
      ],
      [
        "net8_Temporal_Parietal_aperiodic_offset_p95",
        -0.009406840623191184
      ],
      [
        "net8_Dorsal_Attention_aperiodic_offset_median",
        -0.008674794479500052
      ],
      [
        "net8_Default_Mode_aperiodic_offset_p5",
        -0.008293206890897353
      ]
    ]
  },
  {
    "sample_idx": 1,
    "pred_prob": 0.15131540596485138,
    "pred_label": 0,
    "intercept": 0.3402186897388075,
    "features": [
      [
        "global_alpha_peak_pw_p95",
        -0.06644784518207356
      ],
      [
        "net8_Default_Mode_aperiodic_exponent_p95",
        0.03839011587360877
      ],
      [
        "net8_Default_Mode_alpha_peak_bw_p95",
        0.03695186248867766
      ],
      [
        "global_aperiodic_exponent_p95",
        0.03590711760888324
      ],
      [
        "net8_Dorsal_Attention_alpha_peak_pw_p5",
        -0.02549349557202583
      ],
      [
        "net8_Executive_Control_alpha_peak_pw_p95",
        -0.021751214427896952
      ],
      [
        "net8_Dorsal_Attention_aperiodic_offset_p95",
        -0.016134109009367546
      ],
      [
        "net8_Dorsal_Attention_aperiodic_exponent_p5",
        -0.012506594564464185
      ],
      [
        "net8_Visual_aperiodic_offset_p95",
        -0.010982873308075328
      ],
      [
        "net8_Limbic_aperiodic_offset_median",
        0.010169100089903238
      ],
      [
        "net8_Limbic_alpha_peak_bw_p95",
        0.009545154163560958
      ],
      [
        "global_aperiodic_offset_p95",
        -0.006532950399506041
      ],
      [
        "net8_Visual_alpha_peak_cf_p95",
        -0.00504232875602877
      ],
      [
        "net8_Dorsal_Attention_alpha_peak_pw_median",
        -0.00483772146646017
      ],
      [
        "net8_Default_Mode_aperiodic_offset_p5",
        -0.00457054204450791
      ]
    ]
  },
  {
    "sample_idx": 2,
    "pred_prob": 0.859480619430542,
    "pred_label": 1,
    "intercept": 0.34239552118038047,
    "features": [
      [
        "global_alpha_peak_pw_p95",
        -0.06861448380957215
      ],
      [
        "global_aperiodic_exponent_p95",
        0.03906769790610506
      ],
      [
        "net8_Default_Mode_alpha_peak_bw_p95",
        0.03770390018248822
      ],
      [
        "net8_Default_Mode_aperiodic_exponent_p95",
        0.03685360488187161
      ],
      [
        "net8_Executive_Control_alpha_peak_pw_p95",
        -0.025373375109528917
      ],
      [
        "net8_Visual_aperiodic_exponent_p95",
        0.024730159170344677
      ],
      [
        "net8_Temporal_Parietal_alpha_peak_cf_median",
        -0.022336685354012304
      ],
      [
        "net8_Dorsal_Attention_alpha_peak_pw_p5",
        -0.02176721559296859
      ],
      [
        "net8_Visual_alpha_peak_cf_median",
        -0.020659324368699033
      ],
      [
        "global_aperiodic_exponent_p5",
        -0.019431240697666035
      ],
      [
        "net8_Limbic_alpha_peak_cf_median",
        -0.015563756037850207
      ],
      [
        "net8_Default_Mode_aperiodic_exponent_median",
        -0.013860517159564413
      ],
      [
        "net8_Limbic_alpha_peak_cf_p95",
        -0.013146050913703938
      ],
      [
        "net8_Dorsal_Attention_aperiodic_exponent_p5",
        -0.012040323354347116
      ],
      [
        "net8_Dorsal_Attention_alpha_peak_cf_median",
        -0.008466744291611138
      ]
    ]
  },
  {
    "sample_idx": 3,
    "pred_prob": 0.06138743832707405,
    "pred_label": 0,
    "intercept": 0.3387309738603754,
    "features": [
      [
        "global_alpha_peak_pw_p95",
        -0.06426040046130017
      ],
      [
        "global_aperiodic_exponent_p95",
        0.041400928270287705
      ],
      [
        "net8_Default_Mode_aperiodic_exponent_p95",
        0.03753266094654383
      ],
      [
        "net8_Default_Mode_alpha_peak_bw_p95",
        0.03608688134663948
      ],
      [
        "net8_Executive_Control_alpha_peak_pw_p95",
        -0.023530559754548437
      ],
      [
        "net8_Temporal_Parietal_alpha_peak_cf_median",
        -0.02232840054324839
      ],
      [
        "net8_Limbic_alpha_peak_bw_p95",
        0.015988424030535953
      ],
      [
        "global_aperiodic_exponent_p5",
        -0.013985308468582121
      ],
      [
        "net8_Default_Mode_aperiodic_exponent_median",
        -0.013437248173469406
      ],
      [
        "net8_Visual_aperiodic_offset_p95",
        -0.01331655842394495
      ],
      [
        "net8_Limbic_alpha_peak_cf_p95",
        -0.013255372268893822
      ],
      [
        "net8_Dorsal_Attention_aperiodic_exponent_p5",
        -0.013015333151494786
      ],
      [
        "net8_Executive_Control_aperiodic_exponent_p5",
        -0.011217240837829967
      ],
      [
        "net8_Salience_Ventral_Attention_aperiodic_exponent_p5",
        -0.011145695579356659
      ],
      [
        "net8_Limbic_aperiodic_exponent_p95",
        0.010448273538993786
      ]
    ]
  },
  {
    "sample_idx": 4,
    "pred_prob": 0.148711159825325,
    "pred_label": 0,
    "intercept": 0.34248391594460303,
    "features": [
      [
        "net8_Default_Mode_aperiodic_exponent_p95",
        0.03970796081829848
      ],
      [
        "global_aperiodic_exponent_p95",
        0.03925231237019769
      ],
      [
        "net8_Default_Mode_alpha_peak_bw_p95",
        0.03740328671871565
      ],
      [
        "net8_Visual_alpha_peak_cf_median",
        -0.02431536406194117
      ],
      [
        "net8_Dorsal_Attention_alpha_peak_pw_p5",
        -0.023157989019736615
      ],
      [
        "net8_Visual_aperiodic_exponent_p95",
        0.023135927941340364
      ],
      [
        "net8_Temporal_Parietal_alpha_peak_cf_median",
        -0.022638370684336124
      ],
      [
        "net8_Executive_Control_alpha_peak_pw_p95",
        -0.022339038981179137
      ],
      [
        "net8_Limbic_alpha_peak_cf_median",
        -0.01832665463972648
      ],
      [
        "net8_Dorsal_Attention_aperiodic_offset_p95",
        -0.01624982716269669
      ],
      [
        "net8_Limbic_aperiodic_exponent_p95",
        0.013222282691378855
      ],
      [
        "net8_Limbic_alpha_peak_cf_p95",
        -0.012154689938920282
      ],
      [
        "net8_Default_Mode_aperiodic_offset_p5",
        -0.01131592123301764
      ],
      [
        "net8_Somatomotor_aperiodic_offset_median",
        -0.006941602006330909
      ],
      [
        "net8_Temporal_Parietal_aperiodic_offset_median",
        0.006348655553283605
      ]
    ]
  }
]